pyppms/__init__.py
pyppms/booking.py
pyppms/common.py
pyppms/exceptions.py
pyppms/ppms.py
pyppms/system.py
pyppms/user.py
pyppms-3.3.0.dist-info/METADATA
pyppms-3.3.0.dist-info/WHEEL
pyppms-3.3.0.dist-info/RECORD
