Metadata-Version: 2.1
Name: pyppms
Version: 3.3.0
Summary: A Python package to communicate with Stratocore's PUMAPI.
Home-page: https://pypi.org/project/pyppms/
License: GPLv3
Keywords: ppms,pumapi,booking-system,reservation-system
Author: Niko Ehrenfeuchter
Author-email: nikolaus.ehrenfeuchter@unibas.ch
Requires-Python: >=3.9,<4.0
Classifier: License :: Other/Proprietary License
Classifier: Programming Language :: Python :: 3
Classifier: Programming Language :: Python :: 3.9
Classifier: Programming Language :: Python :: 3.10
Classifier: Programming Language :: Python :: 3.11
Requires-Dist: loguru (>=0.7.0,<0.8.0)
Requires-Dist: requests (>=2.31.0,<3.0.0)
Project-URL: Documentation, https://imcf.one/apidocs/pyppms/pyppms.html
Project-URL: Repository, https://github.com/imcf/pyppms
